aliyunswarm/__init__.py
aliyunswarm/common.py
aliyunswarm/config.py
aliyunswarm/http_api.py
aliyunswarm/swarm_api.py
test/__init__.py
test/test.py
aliyunswarm-0.0.20.dist-info/LICENSE
aliyunswarm-0.0.20.dist-info/METADATA
aliyunswarm-0.0.20.dist-info/WHEEL
aliyunswarm-0.0.20.dist-info/top_level.txt
aliyunswarm-0.0.20.dist-info/RECORD
