Metadata-Version: 2.1
Name: aliyunswarm
Version: 0.0.20
Summary: aliyun swarm api
Home-page: http://git.zebrablocklabs.com/wandou_svr/aliyunswarm
Author: rocky
Author-email: lingyu.cheng@gmail.com
License: UNKNOWN
Platform: UNKNOWN
Classifier: Programming Language :: Python :: 3
Classifier: License :: OSI Approved :: MIT License
Classifier: Operating System :: OS Independent
Requires-Python: >=3.6
